AUTHORS.rst
CONTRIBUTING.rst
HISTORY.rst
LICENSE
MANIFEST.in
README.rst
setup.cfg
setup.py
ceg3707/__init__.py
ceg3707/ceg3707.py
ceg3707/cli.py
ceg3707/psmsl.py
ceg3707.egg-info/PKG-INFO
ceg3707.egg-info/SOURCES.txt
ceg3707.egg-info/dependency_links.txt
ceg3707.egg-info/entry_points.txt
ceg3707.egg-info/not-zip-safe
ceg3707.egg-info/requires.txt
ceg3707.egg-info/top_level.txt
docs/Makefile
docs/authors.rst
docs/conf.py
docs/contributing.rst
docs/history.rst
docs/index.rst
docs/installation.rst
docs/make.bat
docs/readme.rst
docs/usage.rst
tests/__init__.py
tests/test_ceg3707.py
tests/test_psmsl.py