Metadata-Version: 1.2
Name: ceg3707
Version: 0.2.0
Summary: CEG3707 Practicls
Home-page: https://github.com/koulali/ceg3707
Author: achraf koulali
Author-email: achraf.koulali@ncl.ac.uk
License: MIT license
Keywords: ceg3707
Platform: UNKNOWN
Classifier: Development Status :: 2 - Pre-Alpha
Classifier: Intended Audience :: Developers
Classifier: License :: OSI Approved :: MIT License
Classifier: Natural Language :: English
Classifier: Programming Language :: Python :: 3
Classifier: Programming Language :: Python :: 3.5
Classifier: Programming Language :: Python :: 3.6
Classifier: Programming Language :: Python :: 3.7
Classifier: Programming Language :: Python :: 3.8
Requires-Python: >=3.5
